pymoodo/__init__.py
pymoodo/Controller.py
pymoodo/HTTPConnection.py
pymoodo/Models.py
pymoodo/WebsocketConnection.py
pymoodo-0.0.4.dist-info/LICENSE
pymoodo-0.0.4.dist-info/WHEEL
pymoodo-0.0.4.dist-info/METADATA
pymoodo-0.0.4.dist-info/RECORD
