Metadata-Version: 2.1
Name: pymoodo
Version: 0.0.4
Summary: Python client to communicate with Moodo API
Home-page: https://github.com/avassem85/pymoodo
License: MIT
Author: Alex van Assem
Author-email: avassem@gmail.com
Requires-Python: >=3.8,<4.0
Classifier: License :: OSI Approved :: MIT License
Classifier: Programming Language :: Python :: 3
Classifier: Programming Language :: Python :: 3.8
Classifier: Programming Language :: Python :: 3.9
Requires-Dist: asyncinit (>=0.2.4,<0.3.0)
Requires-Dist: asyncio (>=3.4.3,<4.0.0)
Requires-Dist: python-engineio (>=3.14.2,<4.0.0)
Requires-Dist: python-socketio[asyncio_client] (>=4.6.1,<5.0.0)
Requires-Dist: requests (>=2.25.1,<3.0.0)
